tms_change_to_gif/__init__.py
tms_change_to_gif/imgtogif.py
tms_change_to_gif-1.0.0.dist-info/licenses/LICENSE
tms_change_to_gif-1.0.0.dist-info/METADATA
tms_change_to_gif-1.0.0.dist-info/WHEEL
tms_change_to_gif-1.0.0.dist-info/top_level.txt
tms_change_to_gif-1.0.0.dist-info/RECORD
