Metadata-Version: 2.4
Name: tms_change_to_gif
Version: 1.0.0
Summary: Test package for distribution
Home-page: 
Download-URL: 
Author: Tomasjoa
Author-email: tomasjoa21@gmail.com
Keywords: GIFCONVERTER,gifconverter
Classifier: Programming Language :: Python :: 3
Classifier: License :: OSI Approved :: MIT License
Classifier: Operating System :: OS Independent
Requires-Python: >=3
License-File: LICENSE
Requires-Dist: pillow
Dynamic: author
Dynamic: author-email
Dynamic: classifier
Dynamic: keywords
Dynamic: license-file
Dynamic: requires-dist
Dynamic: requires-python
Dynamic: summary
